inspect_mate/__init__.py
inspect_mate/__init__.pyc
inspect_mate/getter.py
inspect_mate/getter.pyc
inspect_mate/tester.py
inspect_mate/tester.pyc
inspect_mate/__pycache__/__init__.cpython-34.pyc
inspect_mate/__pycache__/__init__.cpython-35.pyc
inspect_mate/__pycache__/__init__.cpython-36.pyc
inspect_mate/__pycache__/getter.cpython-34.pyc
inspect_mate/__pycache__/getter.cpython-35.pyc
inspect_mate/__pycache__/getter.cpython-36.pyc
inspect_mate/__pycache__/tester.cpython-34.pyc
inspect_mate/__pycache__/tester.cpython-35.pyc
inspect_mate/__pycache__/tester.cpython-36.pyc
inspect_mate/tests/__init__.py
inspect_mate/tests/__init__.pyc
inspect_mate/tests/__pycache__/__init__.cpython-34.pyc
inspect_mate/tests/__pycache__/__init__.cpython-35.pyc
inspect_mate/tests/__pycache__/__init__.cpython-36.pyc
inspect_mate-0.0.2.dist-info/METADATA
inspect_mate-0.0.2.dist-info/RECORD
inspect_mate-0.0.2.dist-info/WHEEL
inspect_mate-0.0.2.dist-info/top_level.txt
